mycustomersegmentation/__init__.py
mycustomersegmentation/mycustomersegmentation.py
mycustomersegmentation-0.1.0.dist-info/AUTHORS.rst
mycustomersegmentation-0.1.0.dist-info/LICENSE
mycustomersegmentation-0.1.0.dist-info/METADATA
mycustomersegmentation-0.1.0.dist-info/WHEEL
mycustomersegmentation-0.1.0.dist-info/top_level.txt
mycustomersegmentation-0.1.0.dist-info/RECORD
