Metadata-Version: 2.1
Name: mycustomersegmentation
Version: 0.1.0
Summary: A python package for customer segmentation
Home-page: https://github.com/Margarita220103/mycustomersegmentation
Author: Margarita Harutyunyan
Author-email: maga220103@gmail.com
License: MIT license
Keywords: mycustomersegmentation
Platform: UNKNOWN
Classifier: Development Status :: 2 - Pre-Alpha
Classifier: Intended Audience :: Developers
Classifier: License :: OSI Approved :: MIT License
Classifier: Natural Language :: English
Classifier: Programming Language :: Python :: 3
Classifier: Programming Language :: Python :: 3.6
Classifier: Programming Language :: Python :: 3.7
Classifier: Programming Language :: Python :: 3.8
Requires-Python: >=3.6
Requires-Dist: pandas
Requires-Dist: matplotlib
Requires-Dist: seaborn
Requires-Dist: scikit-learn
